Metadata-Version: 1.1
Name: mybeans
Version: 0.1
Summary: A example
Home-page: https://github.com/agomez66/examplebeans
Author: agomez66
Author-email: agomez66@xtec.cat
License: LGPL v3
Keywords: It is a example develop
Platform: UNKNOWN
Classifier: Programming Language :: Python
Classifier: Programming Language :: Python :: 2.7
Classifier: Programming Language :: Python :: 3.3
Classifier: Programming Language :: Python :: 3.4
Classifier: Programming Language :: Python :: 3.5
Classifier: Programming Language :: Python :: 3.6
Classifier: Programming Language :: Python :: 3.7
